{
  "id": "dy6",
  "title": "TUI Test Epic",
  "description": "Simple tasks for testing the ticker TUI",
  "notes": "2026-01-13 10:37 - Task 5n3 completed: 2+2=4. Simple test task for TUI testing - no code changes required.\n2026-01-13 10:37 - Task lj7 completed: Module name is github.com/pengelbrecht/ticker. Simple read task - no code changes required.\n2026-01-13 10:37 - Task 3tm completed: 57 .go files in internal/ directory. Simple count task - no code changes required.\n2026-01-13 10:38 - Task 1za completed: ticker CLI has 4 subcommands - run (epics with AI), resume (from checkpoint), checkpoints (list checkpoints), upgrade (self-update). Simple read task - no code changes required.",
  "status": "closed",
  "priority": 2,
  "type": "epic",
  "owner": "peter@engelbrecht.dk",
  "created_by": "peter@engelbrecht.dk",
  "created_at": "2026-01-13T08:48:57.278958Z",
  "updated_at": "2026-01-13T09:38:25.662916Z",
  "closed_at": "2026-01-13T09:38:25.662916Z",
  "closed_reason": "all tasks completed"
}